plunger/__init__.py
plunger/jwt_token.py
plunger/main.py
plunger/sentry_script.py
plunger/version.py
plunger-1.0.1.dist-info/LICENCE.txt
plunger-1.0.1.dist-info/METADATA
plunger-1.0.1.dist-info/WHEEL
plunger-1.0.1.dist-info/entry_points.txt
plunger-1.0.1.dist-info/top_level.txt
plunger-1.0.1.dist-info/RECORD
