Metadata-Version: 2.1
Name: plunger
Version: 1.0.1
Summary: A tool to inspect and clean gitlab's docker registry.
Home-page: https://github.com/factorysh/plunger
Author: Bearstech
Author-email: py@bearstech.com
License: GPLv3
Keywords: docker gitlab registry
Platform: UNKNOWN
Classifier: Intended Audience :: Developers
Classifier: Programming Language :: Python :: 3.5
Classifier: Programming Language :: Python :: 3.6
Classifier: Programming Language :: Python :: 3.7
Classifier: License :: OSI Approved :: GNU Affero General Public License v3
Classifier: Development Status :: 5 - Production/Stable
Requires-Dist: sentry-sdk
Requires-Dist: requests
Requires-Dist: pyjwt
Requires-Dist: cryptography
Requires-Dist: texttable
Provides-Extra: test
Requires-Dist: pytest ; extra == 'test'
Requires-Dist: pytest-cov ; extra == 'test'
Requires-Dist: responses ; extra == 'test'
